tigerasm-0.1.0.dist-info/METADATA
tigerasm-0.1.0.dist-info/WHEEL
tigerasm-0.1.0.dist-info/licenses/LICENSE.txt
tigerasm/__init__.py
tigerasm/tigerasm.cp312-win_amd64.pyd
tigerasm-0.1.0.dist-info/RECORD
