Metadata-Version: 2.4
Name: tigerasm
Version: 0.1.0
Classifier: Programming Language :: Python :: 3
Classifier: Programming Language :: Rust
Classifier: License :: OSI Approved :: GNU Lesser General Public License v3 (LGPLv3)
Classifier: Operating System :: OS Independent
License-File: LICENSE.txt
Summary: TigerASM - Runtime assembler for Python (x86-64 & ARM64)
Keywords: assembly,runtime-assembler,x86-64,ARM64,jit
Author-email: Divyanshu Sinha <divyanshu.singa631@gmail.com>
License: GNU Lesser General Public License v3.0 or later
Requires-Python: >=3.9
Project-URL: Homepage, https://github.com/DivyanshuSinha136/TigerASM
Project-URL: Documentation, https://github.com/DivyanshuSinha136/TigerASM#readme
Project-URL: Repository, https://github.com/DivyanshuSinha136/TigerASM
